{"webpage":"digg.com","answers":[{"assignmentId":"3BWI6RSP7H3L6QCLAD41FGUD9TW7EE","phrase":"go to the home page","version":"v3","webpage":"digg.com","xid":23,"prediction":"1931"},{"assignmentId":"3BWI6RSP7H3L6QCLAD41FGUD9TW7EE","phrase":"watch something","version":"v3","webpage":"digg.com","xid":25,"prediction":"1677"},{"assignmentId":"3COPXFW7XC6DYW8V2L9LDXY3TKYKPI","phrase":"View Store","version":"v3","webpage":"digg.com","xid":38,"prediction":"2529"},{"assignmentId":"3BWI6RSP7H3L6QCLAD41FGUD9TW7EE","phrase":"look for interesting articles","version":"v3","webpage":"digg.com","xid":54,"prediction":"2023"},{"assignmentId":"3COPXFW7XC6DYW8V2L9LDXY3TKYKPI","phrase":"Search Website","version":"v3","webpage":"digg.com","xid":54,"prediction":"12"},{"assignmentId":"354GIDR5ZC08XPX7H7KDFCIM7EH00M","phrase":"Find the search field","version":"v3","webpage":"digg.com","xid":59,"prediction":"12"},{"assignmentId":"354GIDR5ZC08XPX7H7KDFCIM7EH00M","phrase":"Look for a login button","version":"v3","webpage":"digg.com","xid":65,"prediction":"1256"},{"assignmentId":"3COPXFW7XC6DYW8V2L9LDXY3TKYKPI","phrase":"Log In","version":"v3","webpage":"digg.com","xid":65,"prediction":"64"},{"assignmentId":"3COPXFW7XC6DYW8V2L9LDXY3TKYKPI","phrase":"Register for Website","version":"v3","webpage":"digg.com","xid":65,"prediction":"904"},{"assignmentId":"3BWI6RSP7H3L6QCLAD41FGUD9TW7EE","phrase":"read something long","version":"v3","webpage":"digg.com","xid":74,"prediction":"1677"},{"assignmentId":"3BWI6RSP7H3L6QCLAD41FGUD9TW7EE","phrase":"learn about science","version":"v3","webpage":"digg.com","xid":75,"prediction":"3411"},{"assignmentId":"354GIDR5ZC08XPX7H7KDFCIM7EH00M","phrase":"Click on the first article on the site","version":"v3","webpage":"digg.com","xid":92,"prediction":"3325"},{"assignmentId":"3COPXFW7XC6DYW8V2L9LDXY3TKYKPI","phrase":"View Top Story","version":"v3","webpage":"digg.com","xid":92,"prediction":"2529"},{"assignmentId":"354GIDR5ZC08XPX7H7KDFCIM7EH00M","phrase":"Find the about section","version":"v3","webpage":"digg.com","xid":3487,"prediction":"2790"}],"special":[{"type":"prediction","xid":"1931"},{"type":"prediction","xid":"1677"},{"type":"prediction","xid":"2529"},{"type":"prediction","xid":"2023"},{"type":"prediction","xid":"12"},{"type":"prediction","xid":"12"},{"type":"prediction","xid":"1256"},{"type":"prediction","xid":"64"},{"type":"prediction","xid":"904"},{"type":"prediction","xid":"1677"},{"type":"prediction","xid":"3411"},{"type":"prediction","xid":"3325"},{"type":"prediction","xid":"2529"},{"type":"prediction","xid":"2790"}]}