{"webpage":"archive.org-api","answers":[{"assignmentId":"34QN5IT0T0LQFE2ACBXS8RO4QCS80G","phrase":"look at pics","version":"v3","webpage":"archive.org-api","xid":251,"prediction":"1"},{"assignmentId":"30MVJZJNHN7XVPM63BDCQSYB9RGJ9N","phrase":"Enter url in the search field","version":"v3","webpage":"archive.org-api","xid":292,"prediction":"20"},{"assignmentId":"3OE22WJIGJIC14EMWCSCJPXB07IQUC","phrase":"search website","version":"v3","webpage":"archive.org-api","xid":292,"prediction":"17"},{"assignmentId":"30MVJZJNHN7XVPM63BDCQSYB9RGJ9N","phrase":"Look for the upload button","version":"v3","webpage":"archive.org-api","xid":311,"prediction":"310"},{"assignmentId":"30MVJZJNHN7XVPM63BDCQSYB9RGJ9N","phrase":"Find the log in button and click it","version":"v3","webpage":"archive.org-api","xid":317,"prediction":"292"},{"assignmentId":"34QN5IT0T0LQFE2ACBXS8RO4QCS80G","phrase":"get into your account","version":"v3","webpage":"archive.org-api","xid":317,"prediction":"314"},{"assignmentId":"3OE22WJIGJIC14EMWCSCJPXB07IQUC","phrase":"log in to website","version":"v3","webpage":"archive.org-api","xid":317,"prediction":"28"},{"assignmentId":"30MVJZJNHN7XVPM63BDCQSYB9RGJ9N","phrase":"Click on the About Section","version":"v3","webpage":"archive.org-api","xid":320,"prediction":"269"},{"assignmentId":"34QN5IT0T0LQFE2ACBXS8RO4QCS80G","phrase":"get in contact","version":"v3","webpage":"archive.org-api","xid":322,"prediction":"271"},{"assignmentId":"3OE22WJIGJIC14EMWCSCJPXB07IQUC","phrase":"donate to website","version":"v3","webpage":"archive.org-api","xid":330,"prediction":"279"},{"assignmentId":"3OE22WJIGJIC14EMWCSCJPXB07IQUC","phrase":"view jobs","version":"v3","webpage":"archive.org-api","xid":332,"prediction":"281"},{"assignmentId":"3OE22WJIGJIC14EMWCSCJPXB07IQUC","phrase":"volunteer to website","version":"v3","webpage":"archive.org-api","xid":334,"prediction":"283"},{"assignmentId":"30MVJZJNHN7XVPM63BDCQSYB9RGJ9N","phrase":"Go to the homepage","version":"v3","webpage":"archive.org-api","xid":342,"prediction":"1"},{"assignmentId":"34QN5IT0T0LQFE2ACBXS8RO4QCS80G","phrase":"use the api","version":"v3","webpage":"archive.org-api","xid":351,"prediction":"292"}],"special":[{"type":"prediction","xid":"1"},{"type":"prediction","xid":"20"},{"type":"prediction","xid":"17"},{"type":"prediction","xid":"310"},{"type":"prediction","xid":"292"},{"type":"prediction","xid":"314"},{"type":"prediction","xid":"28"},{"type":"prediction","xid":"269"},{"type":"prediction","xid":"271"},{"type":"prediction","xid":"279"},{"type":"prediction","xid":"281"},{"type":"prediction","xid":"283"},{"type":"prediction","xid":"1"},{"type":"prediction","xid":"292"}]}