{"webpage":"opera.com","answers":[{"assignmentId":"3QILPRALQ6PT0AUHDHZQJ3KHY53N86","phrase":"go to home page","version":"v3","webpage":"opera.com","xid":7,"prediction":"29"},{"assignmentId":"3QILPRALQ6PT0AUHDHZQJ3KHY53N86","phrase":"see browsers","version":"v3","webpage":"opera.com","xid":15,"prediction":"15"},{"assignmentId":"39GHHAVOMGLWYJGUMGHL9KNVNZ24JC","phrase":"Find more info about the mobile app","version":"v3","webpage":"opera.com","xid":17,"prediction":"128"},{"assignmentId":"3QILPRALQ6PT0AUHDHZQJ3KHY53N86","phrase":"see apps","version":"v3","webpage":"opera.com","xid":17,"prediction":"17"},{"assignmentId":"3QILPRALQ6PT0AUHDHZQJ3KHY53N86","phrase":"read blogs","version":"v3","webpage":"opera.com","xid":19,"prediction":"19"},{"assignmentId":"39GHHAVOMGLWYJGUMGHL9KNVNZ24JC","phrase":"Find the download button","version":"v3","webpage":"opera.com","xid":29,"prediction":"29"},{"assignmentId":"3JZQSN0I3R4W5XNIYRS13BS6KXUFG7","phrase":"Download a copy of Opera","version":"v3","webpage":"opera.com","xid":29,"prediction":"31"},{"assignmentId":"3QILPRALQ6PT0AUHDHZQJ3KHY53N86","phrase":"get the browser","version":"v3","webpage":"opera.com","xid":29,"prediction":"31"},{"assignmentId":"3JZQSN0I3R4W5XNIYRS13BS6KXUFG7","phrase":"Tell me more about add-on services","version":"v3","webpage":"opera.com","xid":108,"prediction":"132"},{"assignmentId":"3JZQSN0I3R4W5XNIYRS13BS6KXUFG7","phrase":"Go to my opera account","version":"v3","webpage":"opera.com","xid":110,"prediction":"110"},{"assignmentId":"39GHHAVOMGLWYJGUMGHL9KNVNZ24JC","phrase":"Go to the support section","version":"v3","webpage":"opera.com","xid":115,"prediction":"115"},{"assignmentId":"3JZQSN0I3R4W5XNIYRS13BS6KXUFG7","phrase":"Please get me over to the help desk","version":"v3","webpage":"opera.com","xid":115,"prediction":"115"},{"assignmentId":"3JZQSN0I3R4W5XNIYRS13BS6KXUFG7","phrase":"Are there any jobs available for programmers on Opera?","version":"v3","webpage":"opera.com","xid":124,"prediction":"124"},{"assignmentId":"39GHHAVOMGLWYJGUMGHL9KNVNZ24JC","phrase":"Go to the about section","version":"v3","webpage":"opera.com","xid":132,"prediction":"132"}],"special":[{"type":"prediction","xid":"29"},{"type":"prediction","xid":"15"},{"type":"prediction","xid":"128"},{"type":"prediction","xid":"17"},{"type":"prediction","xid":"19"},{"type":"prediction","xid":"29"},{"type":"prediction","xid":"31"},{"type":"prediction","xid":"31"},{"type":"prediction","xid":"132"},{"type":"prediction","xid":"110"},{"type":"prediction","xid":"115"},{"type":"prediction","xid":"115"},{"type":"prediction","xid":"124"},{"type":"prediction","xid":"132"}]}